scripted/__init__.py
scripted/core/__init__.py
scripted/core/bases.py
scripted/core/decorator.py
scripted/core/helpers.py
scripted-0.1.0.dist-info/LICENSE
scripted-0.1.0.dist-info/METADATA
scripted-0.1.0.dist-info/WHEEL
scripted-0.1.0.dist-info/top_level.txt
scripted-0.1.0.dist-info/zip-safe
scripted-0.1.0.dist-info/RECORD
