Metadata-Version: 2.1
Name: scripted
Version: 0.1.0
Summary: MVC framework for CLI applications.
Home-page: http://github.com/infosmith/scripted
Author: infosmith
Author-email: infosmith@protonmail.com
License: MIT
Platform: UNKNOWN
Classifier: Development Status :: 4 - Beta
Classifier: Intended Audience :: Developers 
Classifier: License :: OSI Approved :: MIT License
Classifier: Operating System :: OS Independent
Classifier: Programming Language :: Python
